{
  "timestamp": "2026-06-20T19:50:18.056108+00:00",
  "total_signals": 4,
  "strong_signals": 1,
  "medium_signals": 3,
  "weak_signals": 0,
  "performance_stats": {
    "total_analyses": 4,
    "success_rate": 100.0,
    "avg_analysis_time_sec": 51.11,
    "avg_api_response_time_sec": 0,
    "model_performance": {},
    "recent_analysis_times": [
      [
        "EUR/USD",
        41.51474380493164
      ],
      [
        "GBP/USD",
        46.82405877113342
      ],
      [
        "USD/CHF",
        54.31070947647095
      ],
      [
        "EUR/JPY",
        61.79012680053711
      ]
    ],
    "recent_api_times": []
  }
}