{
  "timestamp": "2025-11-08T04:31:18.170404+00:00",
  "total_signals": 4,
  "strong_signals": 0,
  "medium_signals": 3,
  "weak_signals": 1,
  "performance_stats": {
    "total_analyses": 4,
    "success_rate": 100.0,
    "avg_analysis_time_sec": 48.46,
    "avg_api_response_time_sec": 0,
    "model_performance": {},
    "recent_analysis_times": [
      [
        "EUR/USD",
        37.961159467697144
      ],
      [
        "GBP/USD",
        44.265358209609985
      ],
      [
        "USD/CHF",
        52.29217076301575
      ],
      [
        "EUR/JPY",
        59.33314061164856
      ]
    ],
    "recent_api_times": []
  }
}