{
  "timestamp": "2026-07-13T18:02:26.981516+00:00",
  "total_signals": 4,
  "strong_signals": 0,
  "medium_signals": 0,
  "weak_signals": 4,
  "performance_stats": {
    "total_analyses": 4,
    "success_rate": 100.0,
    "avg_analysis_time_sec": 54.4,
    "avg_api_response_time_sec": 0,
    "model_performance": {},
    "recent_analysis_times": [
      [
        "EUR/USD",
        45.3808171749115
      ],
      [
        "GBP/USD",
        54.4356746673584
      ],
      [
        "USD/CHF",
        56.10483241081238
      ],
      [
        "EUR/JPY",
        61.664790630340576
      ]
    ],
    "recent_api_times": []
  }
}