{
  "timestamp": "2025-11-28T22:27:39.776333+00:00",
  "total_signals": 4,
  "strong_signals": 1,
  "medium_signals": 2,
  "weak_signals": 1,
  "performance_stats": {
    "total_analyses": 4,
    "success_rate": 100.0,
    "avg_analysis_time_sec": 49.81,
    "avg_api_response_time_sec": 0,
    "model_performance": {},
    "recent_analysis_times": [
      [
        "EUR/USD",
        41.548959732055664
      ],
      [
        "GBP/USD",
        46.43885922431946
      ],
      [
        "USD/CHF",
        51.86600208282471
      ],
      [
        "EUR/JPY",
        59.382261991500854
      ]
    ],
    "recent_api_times": []
  }
}