{
  "timestamp": "2026-03-20T05:20:12.584061+00:00",
  "total_signals": 4,
  "strong_signals": 0,
  "medium_signals": 2,
  "weak_signals": 2,
  "performance_stats": {
    "total_analyses": 4,
    "success_rate": 100.0,
    "avg_analysis_time_sec": 49.52,
    "avg_api_response_time_sec": 0,
    "model_performance": {},
    "recent_analysis_times": [
      [
        "EUR/USD",
        37.849071979522705
      ],
      [
        "GBP/USD",
        47.16075873374939
      ],
      [
        "USD/CHF",
        52.56912851333618
      ],
      [
        "EUR/JPY",
        60.48560833930969
      ]
    ],
    "recent_api_times": []
  }
}