{
  "timestamp": "2025-12-16T18:44:14.116365+00:00",
  "total_signals": 4,
  "strong_signals": 1,
  "medium_signals": 2,
  "weak_signals": 1,
  "performance_stats": {
    "total_analyses": 4,
    "success_rate": 100.0,
    "avg_analysis_time_sec": 48.48,
    "avg_api_response_time_sec": 0,
    "model_performance": {},
    "recent_analysis_times": [
      [
        "EUR/USD",
        37.12964749336243
      ],
      [
        "GBP/USD",
        44.821518421173096
      ],
      [
        "USD/CHF",
        52.202478647232056
      ],
      [
        "EUR/JPY",
        59.783738136291504
      ]
    ],
    "recent_api_times": []
  }
}