{
  "timestamp": "2026-02-11T07:16:45.216653+00:00",
  "total_signals": 4,
  "strong_signals": 1,
  "medium_signals": 2,
  "weak_signals": 1,
  "performance_stats": {
    "total_analyses": 4,
    "success_rate": 100.0,
    "avg_analysis_time_sec": 76.83,
    "avg_api_response_time_sec": 0,
    "model_performance": {},
    "recent_analysis_times": [
      [
        "GBP/USD",
        62.24953842163086
      ],
      [
        "EUR/USD",
        69.52331900596619
      ],
      [
        "USD/CHF",
        79.756520986557
      ],
      [
        "EUR/JPY",
        95.77698278427124
      ]
    ],
    "recent_api_times": []
  }
}