{
  "timestamp": "2025-12-15T14:36:33.937694+00:00",
  "total_signals": 4,
  "strong_signals": 2,
  "medium_signals": 2,
  "weak_signals": 0,
  "performance_stats": {
    "total_analyses": 4,
    "success_rate": 100.0,
    "avg_analysis_time_sec": 53.08,
    "avg_api_response_time_sec": 0,
    "model_performance": {},
    "recent_analysis_times": [
      [
        "EUR/USD",
        45.72420358657837
      ],
      [
        "GBP/USD",
        52.657479763031006
      ],
      [
        "USD/CHF",
        54.413989543914795
      ],
      [
        "EUR/JPY",
        59.53195810317993
      ]
    ],
    "recent_api_times": []
  }
}