{
  "timestamp": "2026-06-28T04:43:40.376482+00:00",
  "total_signals": 4,
  "strong_signals": 0,
  "medium_signals": 1,
  "weak_signals": 3,
  "performance_stats": {
    "total_analyses": 4,
    "success_rate": 100.0,
    "avg_analysis_time_sec": 50.16,
    "avg_api_response_time_sec": 0,
    "model_performance": {},
    "recent_analysis_times": [
      [
        "EUR/USD",
        41.11031675338745
      ],
      [
        "GBP/USD",
        45.67072296142578
      ],
      [
        "USD/CHF",
        53.148601770401
      ],
      [
        "EUR/JPY",
        60.7280113697052
      ]
    ],
    "recent_api_times": []
  }
}