[
  {
    "SYMBOL": "USD/CHF",
    "ACTION": "SELL",
    "CONFIDENCE": 7.7,
    "AGREEMENT_LEVEL": 3,
    "AGREEMENT_TYPE": "STRONG_CONSENSUS",
    "VALID_MODELS": 5,
    "TOTAL_MODELS": 6,
    "timestamp": "2025-11-16T08:28:05.158418+00:00",
    "ENTRY": "0.79375",
    "STOP_LOSS": "0.79378",
    "TAKE_PROFIT": "0.79318",
    "RISK_REWARD_RATIO": "18.99",
    "ANALYSIS": "Strong bearish trend with RSI at 54.1, indicating a potential reversal opportunity. Selling at current price with a stop loss slightly above the current price and a take profit at the support level.",
    "ACTUAL_RR_RATIO": 18.99,
    "QUALITY_SCORE": 72.5,
    "TECHNICAL_CONTEXT": {
      "trend": "STRONG_BEARISH",
      "rsi": 54.10162321768581,
      "key_support": 0.7931800099999999,
      "key_resistance": 0.79378001,
      "volatility": 0.08270961875258095,
      "volatility_status": "OPTIMAL"
    }
  }
]