[
  {
    "SYMBOL": "GBP/USD",
    "ACTION": "BUY",
    "CONFIDENCE": 7.2,
    "AGREEMENT_LEVEL": 5,
    "AGREEMENT_TYPE": "STRONG_CONSENSUS",
    "VALID_MODELS": 5,
    "TOTAL_MODELS": 5,
    "timestamp": "2026-01-21T08:43:03.009907+00:00",
    "ENTRY": "1.34406",
    "STOP_LOSS": "1.34403",
    "TAKE_PROFIT": "1.34474",
    "RISK_REWARD_RATIO": "22.67",
    "ANALYSIS": "The strong bullish trend and neutral RSI (49.4) indicate a potential buying opportunity. Entry at 1.34406, stop loss at 1.34395, and take profit at 1.34474 with a risk-reward ratio of 2.0.",
    "ACTUAL_RR_RATIO": 22.67,
    "QUALITY_SCORE": 79.0,
    "TECHNICAL_CONTEXT": {
      "trend": "STRONG_BULLISH",
      "rsi": 49.36249063333698,
      "key_support": 1.34403,
      "key_resistance": 1.34474,
      "volatility": 0.07017092058038488,
      "volatility_status": "OPTIMAL"
    }
  },
  {
    "SYMBOL": "USD/CHF",
    "ACTION": "SELL",
    "CONFIDENCE": 8.0,
    "AGREEMENT_LEVEL": 4,
    "AGREEMENT_TYPE": "STRONG_CONSENSUS",
    "VALID_MODELS": 5,
    "TOTAL_MODELS": 6,
    "timestamp": "2026-01-21T08:43:10.068016+00:00",
    "ENTRY": "0.79191",
    "STOP_LOSS": "0.79230",
    "TAKE_PROFIT": "0.78871",
    "RISK_REWARD_RATIO": "8.21",
    "ANALYSIS": "The strong bearish trend and neutral RSI indicate a potential sell opportunity. The price is near resistance, and a sell could trigger a breakout.",
    "ACTUAL_RR_RATIO": 8.21,
    "QUALITY_SCORE": 76.7,
    "TECHNICAL_CONTEXT": {
      "trend": "STRONG_BEARISH",
      "rsi": 52.4246142013999,
      "key_support": 0.7918666666666666,
      "key_resistance": 0.7923,
      "volatility": 0.07353038991409808,
      "volatility_status": "OPTIMAL"
    }
  },
  {
    "SYMBOL": "EUR/JPY",
    "ACTION": "BUY",
    "CONFIDENCE": 7.2,
    "AGREEMENT_LEVEL": 5,
    "AGREEMENT_TYPE": "STRONG_CONSENSUS",
    "VALID_MODELS": 5,
    "TOTAL_MODELS": 5,
    "timestamp": "2026-01-21T08:43:17.199012+00:00",
    "ENTRY": "184.87310",
    "STOP_LOSS": "184.85274",
    "TAKE_PROFIT": "184.90364",
    "RISK_REWARD_RATIO": "1.5",
    "ANALYSIS": "Strong bullish trend with neutral RSI, indicating a potential continuation of the upward movement.",
    "ACTUAL_RR_RATIO": 1.5,
    "QUALITY_SCORE": 74.5,
    "TECHNICAL_CONTEXT": {
      "trend": "STRONG_BULLISH",
      "rsi": 42.755015747738064,
      "key_support": 184.85274,
      "key_resistance": 184.92937000000003,
      "volatility": 0.06587397344533842,
      "volatility_status": "OPTIMAL"
    }
  }
]