[
  {
    "SYMBOL": "EUR/JPY",
    "ACTION": "SELL",
    "CONFIDENCE": 7.7,
    "AGREEMENT_LEVEL": 3,
    "AGREEMENT_TYPE": "STRONG_CONSENSUS",
    "VALID_MODELS": 5,
    "TOTAL_MODELS": 5,
    "timestamp": "2026-01-07T14:35:07.436032+00:00",
    "ENTRY": "182.95682",
    "STOP_LOSS": "182.99359",
    "TAKE_PROFIT": "182.50158",
    "RISK_REWARD_RATIO": "12.38",
    "ANALYSIS": "Strong bearish trend confirmed, RSI is neutral, suggesting potential for further downside. Stop loss placed above resistance, take profit aiming for a risk-reward of around 1.67.",
    "ACTUAL_RR_RATIO": 12.38,
    "QUALITY_SCORE": 72.0,
    "TECHNICAL_CONTEXT": {
      "trend": "BEARISH",
      "rsi": 44.66383784454581,
      "key_support": 182.93148,
      "key_resistance": 182.99358999999998,
      "volatility": 0.06829645098126638,
      "volatility_status": "OPTIMAL"
    }
  }
]