[
  {
    "SYMBOL": "EUR/JPY",
    "ACTION": "SELL",
    "CONFIDENCE": 7.0,
    "AGREEMENT_LEVEL": 5,
    "AGREEMENT_TYPE": "STRONG_CONSENSUS",
    "VALID_MODELS": 5,
    "TOTAL_MODELS": 5,
    "timestamp": "2026-01-18T12:57:07.168194+00:00",
    "ENTRY": "183.63493",
    "STOP_LOSS": "183.63540",
    "TAKE_PROFIT": "183.63422",
    "RISK_REWARD_RATIO": "1.51",
    "ANALYSIS": "Strong bearish trend with neutral RSI, indicating a potential sell opportunity.",
    "ACTUAL_RR_RATIO": 1.51,
    "QUALITY_SCORE": 74.5,
    "TECHNICAL_CONTEXT": {
      "trend": "BEARISH",
      "rsi": 58.50907691982701,
      "key_support": 183.6299233333333,
      "key_resistance": 183.63539666666665,
      "volatility": 0.06423798760101067,
      "volatility_status": "OPTIMAL"
    }
  }
]