[
  {
    "SYMBOL": "USD/CHF",
    "ACTION": "BUY",
    "CONFIDENCE": 7.0,
    "AGREEMENT_LEVEL": 4,
    "AGREEMENT_TYPE": "STRONG_CONSENSUS",
    "VALID_MODELS": 5,
    "TOTAL_MODELS": 6,
    "timestamp": "2026-04-02T13:47:41.187900+00:00",
    "ENTRY": "0.80029",
    "STOP_LOSS": "0.79981",
    "TAKE_PROFIT": "0.80394",
    "RISK_REWARD_RATIO": "7.6",
    "ANALYSIS": "Strong bullish trend with neutral RSI, indicating a potential buying opportunity. Risk level is low, making it a relatively safe trade.",
    "ACTUAL_RR_RATIO": 7.6,
    "QUALITY_SCORE": 70.7,
    "TECHNICAL_CONTEXT": {
      "trend": "STRONG_BULLISH",
      "rsi": 64.24070523812041,
      "key_support": 0.7998099999999999,
      "key_resistance": 0.8007699999999999,
      "volatility": 0.10566117900786397,
      "volatility_status": "OPTIMAL"
    }
  }
]