[
  {
    "SYMBOL": "EUR/USD",
    "ACTION": "BUY",
    "CONFIDENCE": 7.2,
    "AGREEMENT_LEVEL": 5,
    "AGREEMENT_TYPE": "STRONG_CONSENSUS",
    "VALID_MODELS": 5,
    "TOTAL_MODELS": 7,
    "timestamp": "2025-12-17T04:39:53.005545+00:00",
    "ENTRY": "1.17312",
    "STOP_LOSS": "1.17270",
    "TAKE_PROFIT": "1.17668",
    "RISK_REWARD_RATIO": "8.48",
    "ANALYSIS": "Strong bullish trend with neutral RSI, suggesting a potential upward movement. Low risk level and volatility support this trade.",
    "ACTUAL_RR_RATIO": 8.48,
    "QUALITY_SCORE": 74.9,
    "TECHNICAL_CONTEXT": {
      "trend": "STRONG_BULLISH",
      "rsi": 34.983478024969585,
      "key_support": 1.1727,
      "key_resistance": 1.1732566666666668,
      "volatility": 0.06023128823563978,
      "volatility_status": "OPTIMAL"
    }
  },
  {
    "SYMBOL": "GBP/USD",
    "ACTION": "BUY",
    "CONFIDENCE": 7.2,
    "AGREEMENT_LEVEL": 5,
    "AGREEMENT_TYPE": "STRONG_CONSENSUS",
    "VALID_MODELS": 5,
    "TOTAL_MODELS": 5,
    "timestamp": "2025-12-17T04:39:59.503435+00:00",
    "ENTRY": "1.33983",
    "STOP_LOSS": "1.33920",
    "TAKE_PROFIT": "1.34078",
    "RISK_REWARD_RATIO": "1.51",
    "ANALYSIS": "Strong bullish trend with moderate strength and neutral RSI, indicating a potential buying opportunity with a moderate risk-reward ratio.",
    "ACTUAL_RR_RATIO": 1.51,
    "QUALITY_SCORE": 71.5,
    "TECHNICAL_CONTEXT": {
      "trend": "STRONG_BULLISH",
      "rsi": 43.956595103381105,
      "key_support": 1.33919832,
      "key_resistance": 1.3399833333333333,
      "volatility": 0.07488749078488381,
      "volatility_status": "OPTIMAL"
    }
  }
]