[
  {
    "SYMBOL": "GBP/USD",
    "ACTION": "BUY",
    "CONFIDENCE": 7.2,
    "AGREEMENT_LEVEL": 5,
    "AGREEMENT_TYPE": "STRONG_CONSENSUS",
    "VALID_MODELS": 5,
    "TOTAL_MODELS": 5,
    "timestamp": "2025-11-27T22:27:46.077190+00:00",
    "ENTRY": "1.32384",
    "STOP_LOSS": "1.32377",
    "TAKE_PROFIT": "1.32394",
    "RISK_REWARD_RATIO": "1.43",
    "ANALYSIS": "Strong bullish trend with neutral RSI, indicating a potential buying opportunity. Low risk level and volatility support this decision.",
    "ACTUAL_RR_RATIO": 1.43,
    "QUALITY_SCORE": 74.1,
    "TECHNICAL_CONTEXT": {
      "trend": "BULLISH",
      "rsi": 53.86773406174314,
      "key_support": 1.3237733333333332,
      "key_resistance": 1.3241666666666665,
      "volatility": 0.08310126261683315,
      "volatility_status": "OPTIMAL"
    }
  }
]