[
  {
    "SYMBOL": "EUR/JPY",
    "ACTION": "BUY",
    "CONFIDENCE": 7.2,
    "AGREEMENT_LEVEL": 5,
    "AGREEMENT_TYPE": "STRONG_CONSENSUS",
    "VALID_MODELS": 5,
    "TOTAL_MODELS": 5,
    "timestamp": "2025-11-17T10:33:39.389879+00:00",
    "ENTRY": "179.58299",
    "STOP_LOSS": "179.56933",
    "TAKE_PROFIT": "179.60348",
    "RISK_REWARD_RATIO": "1.5",
    "ANALYSIS": "STRONG_BULLISH trend with neutral RSI, low risk level, and strong support at 179.56933, making a buy opportunity with a risk-reward ratio of 2.0",
    "ACTUAL_RR_RATIO": 1.5,
    "QUALITY_SCORE": 76.0,
    "TECHNICAL_CONTEXT": {
      "trend": "STRONG_BULLISH",
      "rsi": 52.037373605894054,
      "key_support": 179.56933,
      "key_resistance": 179.58746582,
      "volatility": 0.07631170275554598,
      "volatility_status": "OPTIMAL"
    }
  },
  {
    "SYMBOL": "USD/CHF",
    "ACTION": "SELL",
    "CONFIDENCE": 8.0,
    "AGREEMENT_LEVEL": 4,
    "AGREEMENT_TYPE": "STRONG_CONSENSUS",
    "VALID_MODELS": 5,
    "TOTAL_MODELS": 5,
    "timestamp": "2025-11-17T10:33:31.748567+00:00",
    "ENTRY": "0.79467",
    "STOP_LOSS": "0.79471",
    "TAKE_PROFIT": "0.79461",
    "RISK_REWARD_RATIO": "1.5",
    "ANALYSIS": "The strong bearish trend and low RSI value indicate a potential selling opportunity. The price is close to the resistance level, and a sell order can be placed to capture the downward momentum.",
    "ACTUAL_RR_RATIO": 1.5,
    "QUALITY_SCORE": 72.5,
    "TECHNICAL_CONTEXT": {
      "trend": "STRONG_BEARISH",
      "rsi": 54.9138613502664,
      "key_support": 0.7945733266666667,
      "key_resistance": 0.7947077823600001,
      "volatility": 0.08330708864138106,
      "volatility_status": "OPTIMAL"
    }
  },
  {
    "SYMBOL": "GBP/USD",
    "ACTION": "BUY",
    "CONFIDENCE": 6.2,
    "AGREEMENT_LEVEL": 4,
    "AGREEMENT_TYPE": "STRONG_CONSENSUS",
    "VALID_MODELS": 5,
    "TOTAL_MODELS": 5,
    "timestamp": "2025-11-17T10:33:24.543881+00:00",
    "ENTRY": "1.31638",
    "STOP_LOSS": "1.31613",
    "TAKE_PROFIT": "1.32097",
    "RISK_REWARD_RATIO": "18.36",
    "ANALYSIS": "Weak bullish trend with neutral RSI, making it a suitable BUY opportunity with a risk-reward ratio of 1.96.",
    "ACTUAL_RR_RATIO": 18.36,
    "QUALITY_SCORE": 71.0,
    "TECHNICAL_CONTEXT": {
      "trend": "BULLISH",
      "rsi": 52.329411761727364,
      "key_support": 1.3161300000000002,
      "key_resistance": 1.3164900000000002,
      "volatility": 0.0837234798162305,
      "volatility_status": "OPTIMAL"
    }
  }
]