[
  {
    "SYMBOL": "USD/CHF",
    "ACTION": "BUY",
    "CONFIDENCE": 6.3,
    "AGREEMENT_LEVEL": 3,
    "AGREEMENT_TYPE": "STRONG_CONSENSUS",
    "VALID_MODELS": 5,
    "TOTAL_MODELS": 6,
    "timestamp": "2026-04-06T09:20:03.442476+00:00",
    "ENTRY": "0.79747",
    "STOP_LOSS": "0.79740",
    "TAKE_PROFIT": "0.79758",
    "RISK_REWARD_RATIO": "1.57",
    "ANALYSIS": "The trend is neutral with weak strength, but the RSI is at 32.5, indicating a potential buying opportunity. Given the low risk level and reasonable volatility, I'm confident in a buy decision.",
    "ACTUAL_RR_RATIO": 1.57,
    "QUALITY_SCORE": 50.8,
    "TECHNICAL_CONTEXT": {
      "trend": "NEUTRAL",
      "rsi": 32.50793146192428,
      "key_support": 0.7974,
      "key_resistance": 0.79757,
      "volatility": 0.09600844133075692,
      "volatility_status": "OPTIMAL"
    }
  },
  {
    "SYMBOL": "EUR/USD",
    "ACTION": "HOLD",
    "CONFIDENCE": 5.2,
    "AGREEMENT_LEVEL": 4,
    "AGREEMENT_TYPE": "STRONG_CONSENSUS",
    "VALID_MODELS": 5,
    "TOTAL_MODELS": 7,
    "timestamp": "2026-04-06T09:19:49.514597+00:00",
    "ENTRY": "1.15557",
    "STOP_LOSS": "1.15544",
    "TAKE_PROFIT": "1.15562",
    "RISK_REWARD_RATIO": "1.69",
    "ANALYSIS": "Neutral trend and RSI at 67.8, indicating a lack of clear direction. Volatility is low, and risk level is low. Given the weak trend and neutral RSI, it's difficult to make a decisive buy or sell decision.",
    "QUALITY_SCORE": 0.0,
    "TECHNICAL_CONTEXT": {
      "trend": "NEUTRAL",
      "rsi": 67.75937827648445,
      "key_support": 1.155436666666667,
      "key_resistance": 1.1556233333333334,
      "volatility": 0.08974291946057904,
      "volatility_status": "OPTIMAL"
    }
  },
  {
    "SYMBOL": "GBP/USD",
    "ACTION": "HOLD",
    "CONFIDENCE": 4.8,
    "AGREEMENT_LEVEL": 4,
    "AGREEMENT_TYPE": "STRONG_CONSENSUS",
    "VALID_MODELS": 5,
    "TOTAL_MODELS": 6,
    "timestamp": "2026-04-06T09:19:54.609382+00:00",
    "ENTRY": "1.32515",
    "STOP_LOSS": "1.32498",
    "TAKE_PROFIT": "1.32560",
    "RISK_REWARD_RATIO": "1.63",
    "ANALYSIS": "Trend is neutral and weak, RSI is overbought. Despite slight resistance break, lack of bullish trend and overbought RSI suggest caution. A small long position with tight stop loss is possible but the risk is not justified for a strong conviction.",
    "QUALITY_SCORE": 0.0,
    "TECHNICAL_CONTEXT": {
      "trend": "NEUTRAL",
      "rsi": 74.54212024176653,
      "key_support": 1.3249799999999998,
      "key_resistance": 1.32517,
      "volatility": 0.11431103117547108,
      "volatility_status": "OPTIMAL"
    }
  }
]