[
  {
    "SYMBOL": "USD/CHF",
    "ACTION": "HOLD",
    "CONFIDENCE": 4.3,
    "AGREEMENT_LEVEL": 3,
    "AGREEMENT_TYPE": "STRONG_CONSENSUS",
    "VALID_MODELS": 5,
    "TOTAL_MODELS": 6,
    "timestamp": "2026-03-22T03:15:06.913429+00:00",
    "ENTRY": "0.78802",
    "STOP_LOSS": "0.78702",
    "TAKE_PROFIT": "0.78902",
    "RISK_REWARD_RATIO": "1.69",
    "ANALYSIS": "Trend is NEUTRAL and RSI is in a neutral range. While price is near support, there's insufficient bullish evidence to initiate a BUY. A small HOLD with a tight stop-loss and take-profit is appropriate, awaiting clearer directional signals.",
    "QUALITY_SCORE": 0.0,
    "TECHNICAL_CONTEXT": {
      "trend": "NEUTRAL",
      "rsi": 44.448191607085505,
      "key_support": 0.7880000000000001,
      "key_resistance": 0.7880400000000001,
      "volatility": 0.10142358506833035,
      "volatility_status": "OPTIMAL"
    }
  }
]