[
  {
    "SYMBOL": "EUR/USD",
    "ACTION": "HOLD",
    "CONFIDENCE": 5.0,
    "AGREEMENT_LEVEL": 3,
    "AGREEMENT_TYPE": "STRONG_CONSENSUS",
    "VALID_MODELS": 5,
    "TOTAL_MODELS": 7,
    "timestamp": "2025-11-19T06:40:42.772856+00:00",
    "RISK_REWARD_RATIO": "1.8",
    "ANALYSIS": "Extracted from text: \nAlright, let's analyze the EUR/USD market data to make a trading decision. The current price is 1.1...",
    "ENTRY": "N/A",
    "STOP_LOSS": "N/A",
    "TAKE_PROFIT": "N/A",
    "QUALITY_SCORE": 0.0,
    "TECHNICAL_CONTEXT": {
      "trend": "NEUTRAL",
      "rsi": 53.1350139013376,
      "key_support": 1.15883788,
      "key_resistance": 1.15899,
      "volatility": 0.06424069130299037,
      "volatility_status": "OPTIMAL"
    }
  },
  {
    "SYMBOL": "GBP/USD",
    "ACTION": "HOLD",
    "CONFIDENCE": 4.7,
    "AGREEMENT_LEVEL": 3,
    "AGREEMENT_TYPE": "STRONG_CONSENSUS",
    "VALID_MODELS": 5,
    "TOTAL_MODELS": 5,
    "timestamp": "2025-11-19T06:40:49.898197+00:00",
    "ENTRY": "1.31506",
    "STOP_LOSS": "1.31491",
    "TAKE_PROFIT": "1.31535",
    "RISK_REWARD_RATIO": "1.8",
    "ANALYSIS": "The current trend is weak bearish, which suggests a potential reversal. However, the RSI is neutral at 52.0, indicating a lack of clear direction. Therefore, it's best to hold for now and wait for further market developments.",
    "QUALITY_SCORE": 0.0,
    "TECHNICAL_CONTEXT": {
      "trend": "STRONG_BEARISH",
      "rsi": 51.99129006189986,
      "key_support": 1.31491,
      "key_resistance": 1.31535,
      "volatility": 0.08210807246368729,
      "volatility_status": "OPTIMAL"
    }
  },
  {
    "SYMBOL": "USD/CHF",
    "ACTION": "HOLD",
    "CONFIDENCE": 5.3,
    "AGREEMENT_LEVEL": 3,
    "AGREEMENT_TYPE": "STRONG_CONSENSUS",
    "VALID_MODELS": 5,
    "TOTAL_MODELS": 5,
    "timestamp": "2025-11-19T06:40:56.799314+00:00",
    "RISK_REWARD_RATIO": "1.8",
    "ANALYSIS": "Extracted from text: \nOkay, I need to analyze the USD/CHF pair based on the given data and provide a trading decision. Le...",
    "ENTRY": "N/A",
    "STOP_LOSS": "N/A",
    "TAKE_PROFIT": "N/A",
    "QUALITY_SCORE": 0.0,
    "TECHNICAL_CONTEXT": {
      "trend": "NEUTRAL",
      "rsi": 56.78187423847639,
      "key_support": 0.7990699766666666,
      "key_resistance": 0.7993499833333333,
      "volatility": 0.08250482174938706,
      "volatility_status": "OPTIMAL"
    }
  }
]