[
  {
    "SYMBOL": "EUR/USD",
    "ACTION": "HOLD",
    "CONFIDENCE": 4.3,
    "AGREEMENT_LEVEL": 3,
    "AGREEMENT_TYPE": "STRONG_CONSENSUS",
    "VALID_MODELS": 5,
    "TOTAL_MODELS": 7,
    "timestamp": "2026-01-19T22:31:14.371061+00:00",
    "ENTRY": "1.16470",
    "STOP_LOSS": "1.16465",
    "TAKE_PROFIT": "1.16486",
    "RISK_REWARD_RATIO": "1.0",
    "ANALYSIS": "The trend is neutral with strong strength, and the RSI is overbought. Given these conflicting signals and a low risk-reward ratio, a HOLD is the most prudent action.",
    "QUALITY_SCORE": 0.0,
    "TECHNICAL_CONTEXT": {
      "trend": "NEUTRAL",
      "rsi": 70.49439842980621,
      "key_support": 1.164653333333333,
      "key_resistance": 1.1648566666666662,
      "volatility": 0.052873428651679856,
      "volatility_status": "OPTIMAL"
    }
  }
]