[
  {
    "SYMBOL": "EUR/USD",
    "ACTION": "BUY",
    "CONFIDENCE": 7.3,
    "AGREEMENT_LEVEL": 3,
    "AGREEMENT_TYPE": "STRONG_CONSENSUS",
    "VALID_MODELS": 5,
    "TOTAL_MODELS": 7,
    "timestamp": "2026-01-31T14:33:43.399454+00:00",
    "ENTRY": "1.18559",
    "STOP_LOSS": "1.18555",
    "TAKE_PROFIT": "1.18565",
    "RISK_REWARD_RATIO": "1.5",
    "ANALYSIS": "Trend is neutral but showing signs of a potential bullish reversal. RSI is at 33.8, indicating a neutral level. Volatility is low, and risk level is low. This presents a low-risk opportunity to buy.",
    "ACTUAL_RR_RATIO": 1.5,
    "QUALITY_SCORE": 57.7,
    "TECHNICAL_CONTEXT": {
      "trend": "NEUTRAL",
      "rsi": 33.78888960047443,
      "key_support": 1.1855466666666663,
      "key_resistance": 1.1856133333333332,
      "volatility": 0.07878108211049122,
      "volatility_status": "OPTIMAL"
    }
  },
  {
    "SYMBOL": "USD/CHF",
    "ACTION": "HOLD",
    "CONFIDENCE": 5.0,
    "AGREEMENT_LEVEL": 3,
    "AGREEMENT_TYPE": "STRONG_CONSENSUS",
    "VALID_MODELS": 5,
    "TOTAL_MODELS": 5,
    "timestamp": "2026-01-31T14:33:57.341139+00:00",
    "RISK_REWARD_RATIO": "1.8",
    "ANALYSIS": "Extracted from text: \nAlright, so I'm looking at the USD/CHF pair right now. The price is at 0.77201. The trend is neutra...",
    "ENTRY": "N/A",
    "STOP_LOSS": "N/A",
    "TAKE_PROFIT": "N/A",
    "QUALITY_SCORE": 0.0,
    "TECHNICAL_CONTEXT": {
      "trend": "NEUTRAL",
      "rsi": 62.81170574473386,
      "key_support": 0.7719766666666666,
      "key_resistance": 0.7721233333333333,
      "volatility": 0.11073794279935092,
      "volatility_status": "OPTIMAL"
    }
  },
  {
    "SYMBOL": "EUR/JPY",
    "ACTION": "HOLD",
    "CONFIDENCE": 5.0,
    "AGREEMENT_LEVEL": 3,
    "AGREEMENT_TYPE": "STRONG_CONSENSUS",
    "VALID_MODELS": 5,
    "TOTAL_MODELS": 5,
    "timestamp": "2026-01-31T14:34:04.934764+00:00",
    "RISK_REWARD_RATIO": "1.8",
    "ANALYSIS": "Extracted from text: \nAlright, so I'm looking at the EUR/JPY pair right now. The price is at 183.46493, which is just sli...",
    "ENTRY": "N/A",
    "STOP_LOSS": "N/A",
    "TAKE_PROFIT": "N/A",
    "QUALITY_SCORE": 0.0,
    "TECHNICAL_CONTEXT": {
      "trend": "NEUTRAL",
      "rsi": 45.37270285978569,
      "key_support": 183.45792666666668,
      "key_resistance": 183.46887333333333,
      "volatility": 0.08634373661406755,
      "volatility_status": "OPTIMAL"
    }
  }
]