[
  {
    "SYMBOL": "EUR/JPY",
    "ACTION": "BUY",
    "CONFIDENCE": 7.7,
    "AGREEMENT_LEVEL": 3,
    "AGREEMENT_TYPE": "STRONG_CONSENSUS",
    "VALID_MODELS": 5,
    "TOTAL_MODELS": 7,
    "timestamp": "2026-07-11T06:23:23.284514+00:00",
    "ENTRY": "184.61835",
    "STOP_LOSS": "184.60335",
    "TAKE_PROFIT": "184.64085",
    "RISK_REWARD_RATIO": "1.5",
    "ANALYSIS": "Strong neutral trend with low RSI (35.6) suggests potential for a bullish reversal. The price is near support and resistance levels, indicating a possible breakout.",
    "ACTUAL_RR_RATIO": 1.5,
    "QUALITY_SCORE": 57.7,
    "TECHNICAL_CONTEXT": {
      "trend": "NEUTRAL",
      "rsi": 35.63322761550574,
      "key_support": 184.60335333333333,
      "key_resistance": 184.68000666666666,
      "volatility": 0.05988716295520976,
      "volatility_status": "OPTIMAL"
    }
  },
  {
    "SYMBOL": "EUR/USD",
    "ACTION": "SELL",
    "CONFIDENCE": 5.7,
    "AGREEMENT_LEVEL": 3,
    "AGREEMENT_TYPE": "STRONG_CONSENSUS",
    "VALID_MODELS": 5,
    "TOTAL_MODELS": 8,
    "timestamp": "2026-07-11T06:22:56.363331+00:00",
    "RISK_REWARD_RATIO": "1.46",
    "ANALYSIS": "Extracted from text: \nAlright, I'm looking at the EUR/USD pair. The price is currently 1.14114. The trend is showing a st...",
    "ENTRY": "N/A",
    "STOP_LOSS": "1.14127",
    "TAKE_PROFIT": "1.14095",
    "ACTUAL_RR_RATIO": 1.46,
    "QUALITY_SCORE": 52.7,
    "TECHNICAL_CONTEXT": {
      "trend": "STRONG_BEARISH",
      "rsi": 39.26079833144181,
      "key_support": 1.1407866666666666,
      "key_resistance": 1.1412733333333334,
      "volatility": 0.060451742200631875,
      "volatility_status": "OPTIMAL"
    }
  }
]