[
  {
    "SYMBOL": "EUR/USD",
    "ACTION": "HOLD",
    "CONFIDENCE": 5.0,
    "AGREEMENT_LEVEL": 3,
    "AGREEMENT_TYPE": "STRONG_CONSENSUS",
    "VALID_MODELS": 5,
    "TOTAL_MODELS": 7,
    "timestamp": "2026-01-19T08:45:23.256748+00:00",
    "RISK_REWARD_RATIO": "1.8",
    "ANALYSIS": "Extracted from text: \nAlright, let's tackle this query step by step. The user has provided specific instructions for anal...",
    "ENTRY": "N/A",
    "STOP_LOSS": "N/A",
    "TAKE_PROFIT": "N/A",
    "QUALITY_SCORE": 0.0,
    "TECHNICAL_CONTEXT": {
      "trend": "NEUTRAL",
      "rsi": 61.0914778414583,
      "key_support": 1.1624033333333335,
      "key_resistance": 1.162896666666667,
      "volatility": 0.053057356678346164,
      "volatility_status": "OPTIMAL"
    }
  }
]