[
  {
    "SYMBOL": "EUR/USD",
    "ACTION": "SELL",
    "AGREEMENT_LEVEL": 1,
    "AGREEMENT_TYPE": "WEAK_CONSENSUS",
    "VALID_MODELS": 1,
    "TOTAL_MODELS": 5,
    "timestamp": "2025-10-10T08:35:04.236299+00:00",
    "CONFIDENCE": 8.0,
    "ENTRY": "1.15864",
    "STOP_LOSS": "1.16085",
    "TAKE_PROFIT": "1.15414",
    "RISK_REWARD_RATIO": "1.7",
    "EXPIRATION_H": 4,
    "ANALYSIS": "Technical analysis based on strong bearish trend alignment and overbought stochastic conditions"
  },
  {
    "SYMBOL": "GBP/USD",
    "ACTION": "SELL",
    "AGREEMENT_LEVEL": 1,
    "AGREEMENT_TYPE": "WEAK_CONSENSUS",
    "VALID_MODELS": 1,
    "TOTAL_MODELS": 5,
    "timestamp": "2025-10-10T08:35:11.599321+00:00",
    "CONFIDENCE": 8.0,
    "ENTRY": "1.33018",
    "STOP_LOSS": "1.33269",
    "TAKE_PROFIT": "1.32718",
    "RISK_REWARD_RATIO": "1.7",
    "EXPIRATION_H": 4,
    "ANALYSIS": "Technical analysis based on strong bearish trend alignment and neutral momentum bias"
  },
  {
    "SYMBOL": "USD/CHF",
    "ACTION": "BUY",
    "AGREEMENT_LEVEL": 1,
    "AGREEMENT_TYPE": "WEAK_CONSENSUS",
    "VALID_MODELS": 1,
    "TOTAL_MODELS": 5,
    "timestamp": "2025-10-10T08:35:20.167412+00:00",
    "CONFIDENCE": 8.0,
    "ENTRY": "0.80494",
    "STOP_LOSS": "0.80245",
    "TAKE_PROFIT": "0.80744",
    "RISK_REWARD_RATIO": "1.7",
    "EXPIRATION_H": 4,
    "ANALYSIS": "Technical analysis based on strong bullish trend alignment, EMA convergence, and oversold stochastic conditions"
  }
]