[
  {
    "SYMBOL": "EUR/USD",
    "ACTION": "BUY",
    "CONFIDENCE": 6.0,
    "AGREEMENT_LEVEL": 5,
    "AGREEMENT_TYPE": "STRONG_CONSENSUS",
    "VALID_MODELS": 5,
    "TOTAL_MODELS": 7,
    "timestamp": "2026-04-06T22:49:09.123506+00:00",
    "ENTRY": "1.15441",
    "STOP_LOSS": "1.15426",
    "TAKE_PROFIT": "1.15463",
    "RISK_REWARD_RATIO": "1.47",
    "ANALYSIS": "Although the trend is weak bullish, the RSI is neutral and volatility is low, indicating a relatively stable market. The price is at the support level, making it a good entry point for a buy position.",
    "ACTUAL_RR_RATIO": 1.47,
    "QUALITY_SCORE": 59.7,
    "TECHNICAL_CONTEXT": {
      "trend": "BULLISH",
      "rsi": 54.4292788765677,
      "key_support": 1.1542633333333334,
      "key_resistance": 1.1545266666666667,
      "volatility": 0.08967252721887699,
      "volatility_status": "OPTIMAL"
    }
  },
  {
    "SYMBOL": "USD/CHF",
    "ACTION": "BUY",
    "CONFIDENCE": 6.3,
    "AGREEMENT_LEVEL": 3,
    "AGREEMENT_TYPE": "STRONG_CONSENSUS",
    "VALID_MODELS": 5,
    "TOTAL_MODELS": 7,
    "timestamp": "2026-04-06T22:49:25.121790+00:00",
    "ENTRY": "0.79797",
    "STOP_LOSS": "0.79792",
    "TAKE_PROFIT": "0.79807",
    "RISK_REWARD_RATIO": "2.0",
    "ANALYSIS": "The trend is neutral with weak strength, but the RSI is at 43.2, which is not overbought. The price is close to the support level of 0.79792, making it a good entry point for a buy trade.",
    "ACTUAL_RR_RATIO": 2.0,
    "QUALITY_SCORE": 52.7,
    "TECHNICAL_CONTEXT": {
      "trend": "NEUTRAL",
      "rsi": 43.246415836191936,
      "key_support": 0.79792,
      "key_resistance": 0.79807,
      "volatility": 0.09595807593002809,
      "volatility_status": "OPTIMAL"
    }
  },
  {
    "SYMBOL": "GBP/USD",
    "ACTION": "BUY",
    "CONFIDENCE": 6.3,
    "AGREEMENT_LEVEL": 3,
    "AGREEMENT_TYPE": "STRONG_CONSENSUS",
    "VALID_MODELS": 5,
    "TOTAL_MODELS": 7,
    "timestamp": "2026-04-06T22:49:20.422176+00:00",
    "ENTRY": "1.32357",
    "STOP_LOSS": "1.32324",
    "TAKE_PROFIT": "1.32406",
    "RISK_REWARD_RATIO": "1.48",
    "ANALYSIS": "The trend is neutral with weak strength, but the RSI is at 55.0, which is not overbought. Additionally, the volatility is low, making it a good opportunity to enter a long position.",
    "ACTUAL_RR_RATIO": 1.48,
    "QUALITY_SCORE": 51.6,
    "TECHNICAL_CONTEXT": {
      "trend": "NEUTRAL",
      "rsi": 54.9914633190966,
      "key_support": 1.3232433333333335,
      "key_resistance": 1.3237366666666668,
      "volatility": 0.11438827579962044,
      "volatility_status": "OPTIMAL"
    }
  }
]