[
  {
    "SYMBOL": "USD/CHF",
    "ACTION": "BUY",
    "CONFIDENCE": 7.0,
    "AGREEMENT_LEVEL": 4,
    "AGREEMENT_TYPE": "STRONG_CONSENSUS",
    "VALID_MODELS": 5,
    "TOTAL_MODELS": 6,
    "timestamp": "2026-06-11T23:45:38.874789+00:00",
    "ENTRY": "0.79508",
    "STOP_LOSS": "0.79487",
    "TAKE_PROFIT": "0.79540",
    "RISK_REWARD_RATIO": "1.52",
    "ANALYSIS": "Strong bullish trend with weak strength and neutral RSI, indicating a possible breakout. Price is near support level, making it a good entry point.",
    "ACTUAL_RR_RATIO": 1.52,
    "QUALITY_SCORE": 58.8,
    "TECHNICAL_CONTEXT": {
      "trend": "STRONG_BULLISH",
      "rsi": 33.71305022178795,
      "key_support": 0.7948666666666666,
      "key_resistance": 0.7953833333333332,
      "volatility": 0.07489825245218253,
      "volatility_status": "OPTIMAL"
    }
  },
  {
    "SYMBOL": "EUR/JPY",
    "ACTION": "BUY",
    "CONFIDENCE": 6.7,
    "AGREEMENT_LEVEL": 3,
    "AGREEMENT_TYPE": "STRONG_CONSENSUS",
    "VALID_MODELS": 5,
    "TOTAL_MODELS": 6,
    "timestamp": "2026-06-11T23:45:46.559218+00:00",
    "ENTRY": "185.33938",
    "STOP_LOSS": "185.33803",
    "TAKE_PROFIT": "185.34141",
    "RISK_REWARD_RATIO": "1.5",
    "ANALYSIS": "The trend is neutral with weak strength, but the RSI is at 57.4, which is not overbought. Considering the low risk level and the price is close to support, a buy signal is generated.",
    "ACTUAL_RR_RATIO": 1.5,
    "QUALITY_SCORE": 49.0,
    "TECHNICAL_CONTEXT": {
      "trend": "NEUTRAL",
      "rsi": 57.413728295674595,
      "key_support": 185.33803333333333,
      "key_resistance": 185.39894666666666,
      "volatility": 0.049747142497633644,
      "volatility_status": "EXTENDED_RANGE"
    }
  },
  {
    "SYMBOL": "EUR/USD",
    "ACTION": "HOLD",
    "CONFIDENCE": 5.0,
    "AGREEMENT_LEVEL": 3,
    "AGREEMENT_TYPE": "STRONG_CONSENSUS",
    "VALID_MODELS": 5,
    "TOTAL_MODELS": 7,
    "timestamp": "2026-06-11T23:45:24.525428+00:00",
    "ENTRY": "1.15774",
    "STOP_LOSS": "1.15730",
    "TAKE_PROFIT": "1.15795",
    "RISK_REWARD_RATIO": "2.0",
    "ANALYSIS": "The trend is neutral with weak strength, and the RSI is at 62.5, which is not overbought or oversold. The volatility is low, and the risk level is low. Given the neutral trend and lack of clear direction, it's best to hold for now.",
    "QUALITY_SCORE": 0.0,
    "TECHNICAL_CONTEXT": {
      "trend": "NEUTRAL",
      "rsi": 62.4990572257347,
      "key_support": 1.1573,
      "key_resistance": 1.15795,
      "volatility": 0.05795770656214827,
      "volatility_status": "OPTIMAL"
    }
  }
]